Unity3dJiaochengCYuyanBianchengWangFix1/README.md
Unity3dJiaochengCYuyanBianchengWangFix1/__init__.py
Unity3dJiaochengCYuyanBianchengWangFix1/__main__.py
Unity3dJiaochengCYuyanBianchengWangFix1/file.epub
Unity3dJiaochengCYuyanBianchengWangFix1/index.html
Unity3dJiaochengCYuyanBianchengWangFix1/css/__init__.py
Unity3dJiaochengCYuyanBianchengWangFix1/css/annotations.css
Unity3dJiaochengCYuyanBianchengWangFix1/css/main.css
Unity3dJiaochengCYuyanBianchengWangFix1/css/normalize.css
Unity3dJiaochengCYuyanBianchengWangFix1/css/popup.css
Unity3dJiaochengCYuyanBianchengWangFix1/font/__init__.py
Unity3dJiaochengCYuyanBianchengWangFix1/font/fontello.eot
Unity3dJiaochengCYuyanBianchengWangFix1/font/fontello.svg
Unity3dJiaochengCYuyanBianchengWangFix1/font/fontello.ttf
Unity3dJiaochengCYuyanBianchengWangFix1/font/fontello.woff
Unity3dJiaochengCYuyanBianchengWangFix1/img/__init__.py
Unity3dJiaochengCYuyanBianchengWangFix1/img/annotator-glyph-sprite.png
Unity3dJiaochengCYuyanBianchengWangFix1/img/annotator-icon-sprite.png
Unity3dJiaochengCYuyanBianchengWangFix1/img/apple-touch-icon.png
Unity3dJiaochengCYuyanBianchengWangFix1/img/cancelfullscreen.png
Unity3dJiaochengCYuyanBianchengWangFix1/img/close.png
Unity3dJiaochengCYuyanBianchengWangFix1/img/fullscreen.png
Unity3dJiaochengCYuyanBianchengWangFix1/img/loader.gif
Unity3dJiaochengCYuyanBianchengWangFix1/img/menu-icon.png
Unity3dJiaochengCYuyanBianchengWangFix1/img/save.png
Unity3dJiaochengCYuyanBianchengWangFix1/img/saved.png
Unity3dJiaochengCYuyanBianchengWangFix1/img/settings-s.png
Unity3dJiaochengCYuyanBianchengWangFix1/img/settings.png
Unity3dJiaochengCYuyanBianchengWangFix1/img/star.png
Unity3dJiaochengCYuyanBianchengWangFix1/js/__init__.py
Unity3dJiaochengCYuyanBianchengWangFix1/js/epub.js
Unity3dJiaochengCYuyanBianchengWangFix1/js/epub.min.js
Unity3dJiaochengCYuyanBianchengWangFix1/js/epub.min.map
Unity3dJiaochengCYuyanBianchengWangFix1/js/hooks.min.js
Unity3dJiaochengCYuyanBianchengWangFix1/js/hooks.min.map
unity_3d_jiaocheng_c_yuyan_biancheng_wang_fix1-2025.3.24.0.dist-info/METADATA
unity_3d_jiaocheng_c_yuyan_biancheng_wang_fix1-2025.3.24.0.dist-info/WHEEL
unity_3d_jiaocheng_c_yuyan_biancheng_wang_fix1-2025.3.24.0.dist-info/entry_points.txt
unity_3d_jiaocheng_c_yuyan_biancheng_wang_fix1-2025.3.24.0.dist-info/top_level.txt
unity_3d_jiaocheng_c_yuyan_biancheng_wang_fix1-2025.3.24.0.dist-info/RECORD
